raisefunction/__init__.py
raisefunction/core/__init__.py
raisefunction/tests/__init__.py
raisefunction/tests/test_0.py
raisefunction/tests/test_1.py
raisefunction-1.0.2.dist-info/LICENSE.txt
raisefunction-1.0.2.dist-info/METADATA
raisefunction-1.0.2.dist-info/WHEEL
raisefunction-1.0.2.dist-info/top_level.txt
raisefunction-1.0.2.dist-info/RECORD
