Metadata-Version: 2.2
Name: raisefunction
Version: 1.0.2
Summary: This project provides a function that raises errors passed to it.
Author-email: Johannes <johannes-programming@mailfence.com>
License: The MIT License (MIT)
Project-URL: Download, https://pypi.org/project/raisefunction/#files
Project-URL: Index, https://pypi.org/project/raisefunction/
Project-URL: Source, https://github.com/johannes-programming/raisefunction/
Project-URL: Website, https://raisefunction.johannes-programming.online/
Classifier: Development Status :: 5 - Production/Stable
Classifier: Intended Audience :: Developers
Classifier: License :: OSI Approved :: MIT License
Classifier: Natural Language :: English
Classifier: Operating System :: OS Independent
Classifier: Programming Language :: Python
Classifier: Programming Language :: Python :: 3
Classifier: Programming Language :: Python :: 3 :: Only
Classifier: Typing :: Typed
Requires-Python: >=3.8
License-File: LICENSE.txt
Requires-Dist: overloadable>=1.0.9
